xenomapper/__init__.py
xenomapper/mappability.py
xenomapper/xenomapper.py
XenoMapper-1.0.2.dist-info/LICENSE
XenoMapper-1.0.2.dist-info/METADATA
XenoMapper-1.0.2.dist-info/WHEEL
XenoMapper-1.0.2.dist-info/entry_points.txt
XenoMapper-1.0.2.dist-info/top_level.txt
XenoMapper-1.0.2.dist-info/RECORD
